{
  "calm": {
    "label": "Calm",
    "text": {
      "type": "fade-up",
      "stagger": 8,
      "spring": { "damping": 22, "stiffness": 90 }
    },
    "graphics": {
      "blob": false,
      "wipe": false
    }
  },

  "standard": {
    "label": "Standard",
    "text": {
      "type": "slide-up",
      "stagger": 6,
      "spring": { "damping": 16, "stiffness": 140 }
    },
    "graphics": {
      "blob": true,
      "wipe": true
    }
  },

  "dynamic": {
    "label": "Dynamic",
    "text": {
      "type": "slide-up-overshoot",
      "stagger": 4,
      "spring": { "damping": 12, "stiffness": 190 }
    },
    "graphics": {
      "blob": true,
      "wipe": true
    }
  },

  "editorial": {
    "label": "Editorial",
    "text": {
      "type": "fade",
      "stagger": 10,
      "spring": { "damping": 26, "stiffness": 70 }
    },
    "graphics": {
      "blob": false,
      "wipe": true
    }
  }
}
